adarsh_hello/__init__.py
adarsh_hello/main.py
adarsh_hello-0.0.1.dist-info/METADATA
adarsh_hello-0.0.1.dist-info/WHEEL
adarsh_hello-0.0.1.dist-info/top_level.txt
adarsh_hello-0.0.1.dist-info/RECORD
